mfasweep/__init__.py
mfasweep/__main__.py
mfasweep/mfasweep.py
MFASweep.py-1.0.5.dist-info/LICENSE
MFASweep.py-1.0.5.dist-info/METADATA
MFASweep.py-1.0.5.dist-info/WHEEL
MFASweep.py-1.0.5.dist-info/top_level.txt
MFASweep.py-1.0.5.dist-info/RECORD
