Metadata-Version: 2.1
Name: MFASweep.py
Version: 1.0.5
Summary: Test Azure environment for MFA misconfigurations 
Home-page: https://github.com/CasperGN/MFASweep.py
Author: Casper G. Nielsen
Author-email: whopsec@protonmail.com
License: UNKNOWN
Keywords: pentesting enumeration azure mfa-tokens
Platform: UNKNOWN
Classifier: Programming Language :: Python :: 3
Classifier: License :: OSI Approved :: MIT License
Classifier: Environment :: Console
Requires-Python: >=3.4
Requires-Dist: requests (==2.25.0)
Requires-Dist: colorama (==0.4.4)
